kwil/__about__.py
kwil/__init__.py
kwil/exceptions.py
kwil/kwild.py
kwil/main.py
kwil/manager.py
kwil/method.py
kwil/middleware.py
kwil/module.py
kwil/types.py
kwil/_utils/__init__.py
kwil/_utils/action.py
kwil/_utils/dataset.py
kwil/_utils/method_formatters.py
kwil/_utils/naming_converter.py
kwil/_utils/request.py
kwil/_utils/rpcs.py
kwil/_utils/signature.py
kwil/_utils/signing.py
kwil/_utils/transaction.py
kwil/_utils/utils.py
kwil/_utils/validation.py
kwil/_utils/grpc/__init__.py
kwil/_utils/grpc/client.py
kwil/provider/__init__.py
kwil/provider/auto.py
kwil/provider/base.py
kwil/provider/grpc.py
kwil/tx/v1/account_pb2.py
kwil/tx/v1/account_pb2_grpc.py
kwil/tx/v1/broadcast_pb2.py
kwil/tx/v1/broadcast_pb2_grpc.py
kwil/tx/v1/config_pb2.py
kwil/tx/v1/config_pb2_grpc.py
kwil/tx/v1/dataset_pb2.py
kwil/tx/v1/dataset_pb2_grpc.py
kwil/tx/v1/list_pb2.py
kwil/tx/v1/list_pb2_grpc.py
kwil/tx/v1/ping_pb2.py
kwil/tx/v1/ping_pb2_grpc.py
kwil/tx/v1/price_pb2.py
kwil/tx/v1/price_pb2_grpc.py
kwil/tx/v1/query_pb2.py
kwil/tx/v1/query_pb2_grpc.py
kwil/tx/v1/service_pb2.py
kwil/tx/v1/service_pb2_grpc.py
kwil/tx/v1/tx_pb2.py
kwil/tx/v1/tx_pb2_grpc.py
kwil_typing/__init__.py
kwil_typing/kvm.py
kwil_utils/__init__.py
kwil_utils/types.py
kwil-0.1.0.dist-info/METADATA
kwil-0.1.0.dist-info/WHEEL
kwil-0.1.0.dist-info/top_level.txt
kwil-0.1.0.dist-info/RECORD
